.bumpversion.cfg
.gitignore
LICENSE.txt
MANIFEST.in
Makefile
README.txt
procgraph_packages.py
pypackage.mk
requirements.txt
setup.py
shippable.yml
docs/.gitignore
docs/Makefile
docs/TODO.txt
docs/docs.mk
docs/epydoc.cfg
docs/examples.rst
docs/gitadd.zsh
docs/sphinxtogithub.py
docs/source/.gitignore
docs/source/api.rst
docs/source/conf.py
docs/source/definitions.txt
docs/source/download.html
docs/source/faq.rst
docs/source/fork.html
docs/source/index.rst
docs/source/install.rst
docs/source/library.rst
docs/source/nodes.rst
docs/source/packaging.rst
docs/source/pgdoc.inc
docs/source/plots.rst
docs/source/running.rst
docs/source/why.rst
docs/source/writing_a_block.rst
docs/source/writing_blocks_classes.rst
docs/source/writing_blocks_models.rst
docs/source/writing_blocks_simple.rst
docs/source/writing_generators.rst
docs/source/my_static/procgraph.css
docs/source/my_templates/layout.html
docs/source/tutorial/.gitignore
docs/source/tutorial/coastguard.mp4
docs/source/tutorial/index.rst
docs/source/tutorial/run_all.sh
docs/source/tutorial/tutorial00.txt
docs/source/tutorial/tutorial00_basics.pg
docs/source/tutorial/tutorial01.txt
docs/source/tutorial/tutorial01_signals.pg
docs/source/tutorial/tutorial02.txt
docs/source/tutorial/tutorial02_sync.pg
docs/source/tutorial/tutorial03.txt
docs/source/tutorial/tutorial03_config.pg
docs/source/tutorial/tutorial04.txt
docs/source/tutorial/tutorial04_models.pg
docs/source/tutorial/tutorial05.txt
docs/source/tutorial/tutorial05_config_advanced.pg
docs/source/tutorial/tutorial06.txt
docs/source/tutorial/tutorial06_signals_advanced.pg
docs/source/tutorial/tutorial07.txt
docs/source/tutorial/tutorial07_blocks.py
docs/source/tutorial/tutorial07_simple_blocks.pg
docs/source/tutorial/tutorial08.txt
docs/source/tutorial/tutorial08_blocks.py
docs/source/tutorial/tutorial08_simple_blocks_conf.pg
docs/source/tutorial/tutorial09.txt
docs/source/tutorial/tutorial09_best_practices.pg
docs/source/tutorial/tutorial09_blocks.py
src/procgraph.egg-info/PKG-INFO
src/procgraph.egg-info/SOURCES.txt
src/procgraph.egg-info/dependency_links.txt
src/procgraph.egg-info/entry_points.txt
src/procgraph.egg-info/not-zip-safe
src/procgraph.egg-info/requires.txt
src/procgraph.egg-info/top_level.txt
