Metadata-Version: 1.1
Name: procgraph
Version: 1.10.10
Summary: ProcGraph ("processing graph") is a Python library for rapid prototyping of processing pipelines for logged and realtime data.
Home-page: http://andreacensi.github.com/procgraph/
Author: Andrea Censi
Author-email: censi@mit.edu
License: LGPL
Download-URL: http://github.com/AndreaCensi/procgraph/tarball/1.10.10
Platform: UNKNOWN
Classifier: Development Status :: 4 - Beta
Classifier: Intended Audience :: Developers
Classifier: Intended Audience :: Science/Research
Classifier: License :: OSI Approved :: GNU Library or Lesser General Public License (LGPL)
Classifier: Topic :: Scientific/Engineering
